{
  "title": "The Ending George R.R. Martin Hinted At #got #shorts",
  "description": "The ending of Game of Thrones may not have been wrong—just misunderstood. George R.R. Martin’s story was never about heroes winning, but about the cost of power and survival. This is the deeper meaning behind the ending. #GameOfThrones #EndingExplained #Shorts",
  "scenes": [
    {
      "scene_number": 1,
      "scene_type": "hook",
      "narration": "The ending of Game of Thrones felt unexpected to many—but it may have followed the story’s true themes all along.",
      "image_prompt": "empty Iron Throne room covered in ash and silence, cinematic dark tone, vertical 1080x1920",
      "duration": 4,
      "effect": "zoom_in"
    },
    {
      "scene_number": 2,
      "narration": "George R. R. Martin’s world was never about heroes winning—it was about choices, consequences, and survival.",
      "image_prompt": "multiple characters fading into shadows, moral ambiguity theme, vertical 1080x1920",
      "duration": 4,
      "effect": "ken_burns_in"
    },
    {
      "scene_number": 3,
      "narration": "Power in Westeros was never stable, and every ruler who sought it paid a price.",
      "image_prompt": "crown melting into ash, symbol of unstable power, vertical 1080x1920",
      "duration": 4,
      "effect": "pulse"
    },
    {
      "scene_number": 4,
      "narration": "Daenerys’ fall was not sudden—it was the result of a path shaped by loss, belief, and unchecked power.",
      "image_prompt": "Daenerys in fire with conflicted expression, tragic tone, vertical 1080x1920",
      "duration": 4,
      "effect": "parallax_up"
    },
    {
      "scene_number": 5,
      "narration": "Jon Snow’s final choice mirrored the ancient stories—sacrifice for the greater good, even when it breaks everything.",
      "image_prompt": "Jon in shadow holding sword, emotional weight, vertical 1080x1920",
      "duration": 4,
      "effect": "pan_left"
    },
    {
      "scene_number": 6,
      "narration": "The throne itself was destroyed, showing that the cycle of power had to end, not continue.",
      "image_prompt": "Iron Throne melting under dragonfire, symbolic destruction, vertical 1080x1920",
      "duration": 4,
      "effect": "zoom_rapid"
    },
    {
      "scene_number": 7,
      "narration": "Bran becoming king was not about strength—but about memory, perspective, and breaking the old system.",
      "image_prompt": "Bran seated as king with ravens and shadows of history around him, vertical 1080x1920",
      "duration": 4,
      "effect": "drift_right"
    },
    {
      "scene_number": 8,
      "narration": "The ending was not meant to satisfy expectations—but to reflect the complexity of power and human nature.",
      "image_prompt": "world rebuilding slowly from ashes, uncertain future, vertical 1080x1920",
      "duration": 4,
      "effect": "breathe"
    },
    {
      "scene_number": 9,
      "narration": "In this world, there are no perfect endings—only outcomes shaped by difficult choices.",
      "image_prompt": "multiple characters walking separate paths into unknown horizon, vertical 1080x1920",
      "duration": 4,
      "effect": "diagonal_tr_bl"
    },
    {
      "scene_number": 10,
      "scene_type": "final",
      "narration": "Because the true ending of Game of Thrones was never about who won—but what the world became after.",
      "image_prompt": "Westeros landscape at dawn after destruction, calm but changed, cinematic ending, vertical 1080x1920",
      "duration": 4,
      "effect": "zoom_out"
    }
  ],
  "total_duration": 44
}